{
  "date": "2026-04-03",
  "total_events": 4,
  "by_company": {
    "auo": {
      "count": 1,
      "sentiment_avg": 0.0
    }
  },
  "by_topic": {
    "panel_price": {
      "count": 2,
      "sentiment_avg": 0.0
    },
    "oled_penetration": {
      "count": 2,
      "sentiment_avg": 0.0
    },
    "earnings": {
      "count": 1,
      "sentiment_avg": 0.0
    },
    "it_panel_demand": {
      "count": 1,
      "sentiment_avg": 0.0
    },
    "mini_led": {
      "count": 1,
      "sentiment_avg": 0.5
    }
  },
  "baselines_used": {
    "companies": {},
    "topics": {}
  },
  "supply_chain_activity": []
}